backupfolders/__init__.py
backupfolders/backupfolders.py
backupfolders-0.6.dist-info/LICENSE
backupfolders-0.6.dist-info/METADATA
backupfolders-0.6.dist-info/WHEEL
backupfolders-0.6.dist-info/top_level.txt
backupfolders-0.6.dist-info/RECORD
