Metadata-Version: 2.1
Name: backupfolders
Version: 0.6
Summary: Backup your folders from one location to another with ease.
Home-page: https://github.com/Fahad-codecraft
Author: Fahad Devnikar
Author-email: devnikarfahad@gmail.com
License: MIT
Keywords: backup,folders,files
Classifier: Development Status :: 3 - Alpha
Classifier: Intended Audience :: Developers
Classifier: Topic :: Software Development :: Build Tools
Classifier: License :: OSI Approved :: MIT License
Classifier: Programming Language :: Python :: 3
License-File: LICENSE
